Workbook

Sheet QR Code packing matrix with wei
A1: Sl.no | B1: Customer name | C1: Customer part no | D1: ipr Ref no | E1: Qty | F1: Min Weight | G1: Max Weight
A2: 1 | B2: Dana | C2: 10149080 | D2: 421 | E2: 40 | F2: 14.97 | G2: 15.25 | H2: =VLOOKUP(C2:C26,Sheet2!A:B,2,FALSE) -> 24
A3: 2 | B3: Dana | C3: 100402090 | D3: 291 | E3: 40 | F3: 15.7 | G3: 16 | H3: =VLOOKUP(C3:C27,Sheet2!A:B,2,FALSE) -> #N/A
A4: 3 | B4: Dana | C4: 2006102 | D4: 213 | E4: 40 | F4: 16.24 | G4: 16.74 | H4: =VLOOKUP(C4:C28,Sheet2!A:B,2,FALSE) -> 24
A5: 4 | B5: Dana | C5: 10306250 | D5: 464 | E5: 30 | F5: 17.9 | G5: 17.96 | H5: =VLOOKUP(C5:C29,Sheet2!A:B,2,FALSE) -> 24
A6: 5 | B6: AAM | C6: 40225752 | D6: 427 | E6: 30 | F6: 13.63 | G6: 13.68 | H6: =VLOOKUP(C6:C30,Sheet2!A:B,2,FALSE) -> #N/A
A7: 6 | B7: DAIPL | C7: 10129664 | D7: 362 | E7: 100 | F7: 18.2 | G7: 18.26 | H7: =VLOOKUP(C7:C31,Sheet2!A:B,2,FALSE) -> #N/A
A8: 7 | B8: Dana | C8: 10026815 | D8: 263 | E8: 40 | F8: 16.64 | G8: 17.148425 | H8: =VLOOKUP(C8:C32,Sheet2!A:B,2,FALSE) -> 24
A9: 8 | B9: Dana | C9: 2006101 | D9: 214 | E9: 40 | F9: 11.82985 | G9: 12.19015 | H9: =VLOOKUP(C9:C33,Sheet2!A:B,2,FALSE) -> 45
A10: 9 | B10: Dana | C10: 10116943 | D10: 356 | E10: 30 | F10: 18.2225 | G10: 18.7775 | H10: =VLOOKUP(C10:C34,Sheet2!A:B,2,FALSE) -> 24
A11: 10 | B11: Dana | C11: 10116941 | D11: 357 | E11: 20 | F11: 18.66575 | G11: 19.23425 | H11: =VLOOKUP(C11:C35,Sheet2!A:B,2,FALSE) -> 24
A12: 11 | B12: Dana | C12: 10116937 | D12: 358 | E12: 30 | F12: 22.453075 | G12: 23.136925 | H12: =VLOOKUP(C12:C36,Sheet2!A:B,2,FALSE) -> 24
A13: 12 | B13: Dana | C13: 10116939 | D13: 359 | E13: 40 | F13: 15.459575 | G13: 15.930425 | H13: =VLOOKUP(C13:C37,Sheet2!A:B,2,FALSE) -> 24
... A26: 25 | B26: Dana | C26: 10036600 | D26: 302 | E26: 100 | F26: 9.062 | G26: 9.338 | H26: =VLOOKUP(C26:C50,Sheet2!A:B,2,FALSE) -> #N/A

Sheet QR Code packing matrix
A1: Packing part list matrix
A3: # | B3: IPR Part no | C3: Customer part no | D3: Model | E3: Part qty/Primary carton box | F3: Primary Carton box qty/Master Carton Box | G3: Part qty/Master Carton box | H3: Remarks | I3: matrial code
A4: 1 | B4: 422 | C4: 10152525 | D4: JL GEN | E4: 30 | F4: 24 | G4: 720 | I4: 14005007
A5: 2 | B5: 421 | C5: 10149080 | D5: JL GEN | E5: 40 | F5: 24 | G5: 960 | I5: 14005314
A6: 3 | B6: 464 | C6: 10306250 | D6: JL GEN | E6: 30 | F6: 24 | G6: 720 | I6: 14000025
A7: 4 | B7: 291 | C7: 10040290 | D7: JL | E7: 40 | F7: 24 | G7: 960 | I7: 14000073
A8: 5 | B8: 263 | C8: 10026815 | D8: JL | E8: 40 | F8: 24 | G8: 960 | I8: 14000021
A9: 6 | B9: 213 | C9: 2006102 | D9: JL | E9: 40 | F9: 24 | G9: 960 | I9: 14004852
A10: 7 | B10: 214 | C10: 2006101 | D10: JL | E10: 40 | F10: 45 | G10: 1800 | I10: 14004854
A11: 8 | B11: 356 | C11: 10116943 | D11: TREX | E11: 30 | F11: 24 | G11: 720 | I11: 14000052
A12: 9 | B12: 357 | C12: 10116941 | D12: TREX | E12: 20 | F12: 24 | G12: 480 | I12: 14000057
A13: 10 | B13: 358 | C13: 10116937 | D13: TREX | E13: 30 | F13: 24 | G13: 720 | I13: 14000037
A14: 11 | B14: 359 | C14: 10116939 | D14: TREX | E14: 40 | F14: 24 | G14: 960 | I14: 14005094
A15: 12 | B15: 432 | C15: 10183422 | D15: P708 EDL | E15: 15 | F15: 24 | G15: 360 | I15: 14000062
... A18: 15 | B18: 434 | C18: 10183421 | D18: P708 EDL | E18: 40 | F18: 24 | G18: 960 | I18: 14005002
A19: 16 | B19: 438 | C19: 54920 | D19: P708 | E19: N/A | F19: N/A | G19: 200 | I19: 14005003
A20: 17 | B20: 439 | C20: 2008157 | D20: P708 | E20: N/A | F20: N/A | G20: 200 | I20: 14000106
A21: 18 | B21: 440 | C21: 2015925 | D21: P708 | E21: N/A | F21: N/A | G21: 200 | I21: 14004853
A22: 19 | B22: 416 | C22: 54919 | D22: P708 | E22: N/A | F22: N/A | G22: 360 | I22: 14004954
I23: 14000024
I24: 14000015
I25: 14000047
I26: 14000059
I27: 14000018
I28: 14004851
I29: 14000054
I30: 14000020
I31: 14000023
I32: 14000074

Sheet invoice csv formate field
A1: BILLING DOCUMENT | B1: BILLING DATE | C1: BILLING DOCUMENT TYP | D1: BILLING DES | E1: COMPANY CODE | F1: SALES ORDER | G1: SALES ORDER ITEM | H1: CUSTOMER NO. | I1: CUSTOMER NAME | J1: CUSTOMER PO No. | K1: CUSTOMER PO Date | L1: SALES ORGANISATION | M1: DISTRIBUTION CHANNEL | N1: DIVISION | O1: PLANT | P1: ITEM CODE | Q1: MATERIAL NAME | R1: MATERIAL DESCRIPTION | S1: CUSTOMER PART NUMBER | T1: CUSTOMER PART NAME | U1: INCOTERMS | V1: HSN/SAC | W1: COUNTRY NAME | X1: REGION | Y1: ITEM VALUE | Z1: DISCOUNT % | AA1: BILLED QTY | AB1: ITEM_TOTALVALUE | AC1: DISCOUNTED VALUE | AD1: TOTAL VALUE AFTER DI | AE1: CURRANCY | AF1: FI DOCUMENT | AG1: EXCHANGE RATE | AH1: FINAL VALUE | AI1: JOIG% | AJ1: JOIG TAX VALUE | AK1: JOCG% | AL1: JOCG TAX VALUE | AM1: JOSG% | AN1: JOSG TAX VALUE | AO1: TOTAL TAX ITEM WISE | AP1: PACKING COST | AQ1: TOTAL PACKING COST | AR1: TOTAL TCS/SALE | AS1: TCS TAX/SALES% | AT1: TCS TAX /SCRAP% | AU1: TOTAL TCS/SCRAP | AV1: TOTAL INV VALUE | AW1: IRN NO. | AX1: TRANSPORTER NAME | AY1: TRANSPORT MODE | AZ1: TRANSPORTER NO. | BA1: TRANSPORT DATE | BB1: TRANSPORT DATE | BC1: VECHILE NO. | BD1: EWAY BILL NO. | BE1: EWAY BILL DT | BF1: LR NO. | BG1: LR DATE | BH1: GRN NO. | BI1: GRN DATE | BJ1: REMARKS

Sheet Sheet1
B2: COMPANY_CODE | C2: $table->string(' | D2: '); | E2: =C2&B2&D2 -> $table->string('COMPANY_CODE');
B3: SALES_ORDER | C3: $table->string(' | D3: '); | E3: =C3&B3&D3 -> $table->string('SALES_ORDER');
B4: SALES_ORDER_ITEM | C4: $table->string(' | D4: '); | E4: =C4&B4&D4 -> $table->string('SALES_ORDER_ITEM');
B5: CUSTOMER_NO. | C5: $table->string(' | D5: '); | E5: =C5&B5&D5 -> $table->string('CUSTOMER_NO.');
B6: CUSTOMER_NAME | C6: $table->string(' | D6: '); | E6: =C6&B6&D6 -> $table->string('CUSTOMER_NAME');
B7: CUSTOMER_PO_No. | C7: $table->string(' | D7: '); | E7: =C7&B7&D7 -> $table->string('CUSTOMER_PO_No.');
B8: CUSTOMER_PO_Date | C8: $table->string(' | D8: '); | E8: =C8&B8&D8 -> $table->string('CUSTOMER_PO_Date');
B9: SALES_ORGANISATION | C9: $table->string(' | D9: '); | E9: =C9&B9&D9 -> $table->string('SALES_ORGANISATION');
B10: DISTRIBUTION_CHANNEL | C10: $table->string(' | D10: '); | E10: =C10&B10&D10 -> $table->string('DISTRIBUTION_CHANNEL');
B11: DIVISION | C11: $table->string(' | D11: '); | E11: =C11&B11&D11 -> $table->string('DIVISION');
B12: PLANT | C12: $table->string(' | D12: '); | E12: =C12&B12&D12 -> $table->string('PLANT');
B13: ITEM_CODE | C13: $table->string(' | D13: '); | E13: =C13&B13&D13 -> $table->string('ITEM_CODE');
... B59: REMARKS | C59: $table->string(' | D59: '); | E59: =C59&B59&D59 -> $table->string('REMARKS');

Sheet Sheet2
A1: 10152525 | B1: 24
A2: 10149080 | B2: 24
A3: 10306250 | B3: 24
A4: 10040290 | B4: 24
A5: 10026815 | B5: 24
A6: 2006102 | B6: 24
A7: 2006101 | B7: 45
A8: 10116943 | B8: 24
A9: 10116941 | B9: 24
A10: 10116937 | B10: 24
A11: 10116939 | B11: 24
A12: 10183422 | B12: 24
... A15: 10183421 | B15: 24
A16: 54920 | B16: N/A
A17: 2008157 | B17: N/A
A18: 2015925 | B18: N/A
A19: 54919 | B19: N/A
